optelier/__init__.py
optelier/cli.py
optelier/core.py
optelier/problems/__init__.py
optelier/problems/examples/__init__.py
optelier/problems/examples/feature.py
optelier/problems/examples/function_test.py
optelier/problems/examples/untrusted.py
optelier/problems/secure.py
optelier/problems/sum_json.py
optelier/problems/text_regex.py
optelier/problems/validation.py
optelier-0.1.1.dist-info/LICENSE
optelier-0.1.1.dist-info/METADATA
optelier-0.1.1.dist-info/WHEEL
optelier-0.1.1.dist-info/entry_points.txt
optelier-0.1.1.dist-info/RECORD
