Metadata-Version: 2.3
Name: optelier
Version: 0.1.1
Summary: DX-first evaluator: submission -> evaluation -> score
License: MIT
Keywords: optimization,modeling,analytics,evaluation,submission
Author: Stuart
Author-email: stuart@example.com
Requires-Python: >=3.11,<4.0
Classifier: Development Status :: 3 - Alpha
Classifier: Intended Audience :: Developers
Classifier: License :: OSI Approved :: MIT License
Classifier: Programming Language :: Python :: 3
Classifier: Programming Language :: Python :: 3.11
Classifier: Programming Language :: Python :: 3.12
Classifier: Programming Language :: Python :: 3.13
Classifier: Programming Language :: Python :: 3.10
Requires-Dist: docker (>=6.0.0,<7.0.0)
Requires-Dist: numpy (>=2.3.4,<3.0.0)
Requires-Dist: pandas (>=2.3.3,<3.0.0)
Project-URL: Homepage, https://github.com/yourusername/optelier
Project-URL: Repository, https://github.com/yourusername/optelier
